showerpipe/__init__.py
showerpipe/_version.py
showerpipe/base.py
showerpipe/generator.py
showerpipe/lhe.py
showerpipe/py.typed
showerpipe-0.2.7.dist-info/LICENSE.txt
showerpipe-0.2.7.dist-info/METADATA
showerpipe-0.2.7.dist-info/WHEEL
showerpipe-0.2.7.dist-info/top_level.txt
showerpipe-0.2.7.dist-info/RECORD
