Metadata-Version: 2.1
Name: showerpipe
Version: 0.2.7
Summary: Data pipeline tools for particle shower and hadronisation.
Home-page: https://github.com/jacanchaplais/showerpipe
Author: Jacan Chaplais
Author-email: jacanchaplais@gmail.com
License: BSD 3-Clause License
Project-URL: Documentation, https://showerpipe.readthedocs.io
Classifier: Programming Language :: Python :: 3
Classifier: License :: OSI Approved :: BSD License
Classifier: Operating System :: OS Independent
License-File: LICENSE.txt
Requires-Dist: requests
Requires-Dist: lxml
Requires-Dist: numpy
Requires-Dist: pandas
Requires-Dist: rich
Provides-Extra: dev
Requires-Dist: pre-commit (==2.19.0) ; extra == 'dev'
Requires-Dist: flake8 (==3.9.2) ; extra == 'dev'
Requires-Dist: tox (==3.24.3) ; extra == 'dev'
Requires-Dist: pytest (==6.2.5) ; extra == 'dev'
Requires-Dist: pytest-cov (==2.12.1) ; extra == 'dev'
Requires-Dist: hypothesis (==6.62.0) ; extra == 'dev'
Requires-Dist: mypy (==0.910) ; extra == 'dev'
